{
	"format_version": "1.12.0",
	"minecraft:geometry": [
		{
			"description": {
				"identifier": "geometry.turthug",
				"texture_width": 128,
				"texture_height": 128,
				"visible_bounds_width": 3,
				"visible_bounds_height": 3.5,
				"visible_bounds_offset": [0, 1.25, 0]
			},
			"bones": [
				{
					"name": "turthug",
					"pivot": [0, 0, 0]
				},
				{
					"name": "body",
					"parent": "turthug",
					"pivot": [0, 0, 0]
				},
				{
					"name": "torso",
					"parent": "body",
					"pivot": [0, 3.8, 0],
					"cubes": [
						{"origin": [-6.4, 9.05, -7], "size": [13, 7, 14], "uv": [0, 21]},
						{"origin": [-5.5, 15.95, -5.5], "size": [11, 7, 11], "uv": [0, 42]},
						{"origin": [3.27316, 18.8, 3.60537], "size": [4, 0, 3], "pivot": [5.06453, 18.8, 5.33734], "rotation": [0, -75, 0], "uv": [0, 31]},
						{"origin": [3.77316, 19.8, 3.60537], "size": [4, 0, 3], "pivot": [5.06453, 18.8, 5.33734], "rotation": [32.94581, -72.03614, -34.26563], "uv": [0, 31]},
						{"origin": [-7.27316, 18.8, 3.60537], "size": [4, 0, 3], "pivot": [-5.06453, 18.8, 5.33734], "rotation": [0, 75, 0], "uv": [0, 31], "mirror": true},
						{"origin": [-7.77316, 19.8, 3.60537], "size": [4, 0, 3], "pivot": [-5.06453, 18.8, 5.33734], "rotation": [32.94581, 72.03614, 34.26563], "uv": [0, 31], "mirror": true},
						{"origin": [-6.5, 8.9, -7], "size": [13, 7.2, 14], "inflate": 0.2, "uv": [0, 0]}
					]
				},
				{
					"name": "coral",
					"parent": "torso",
					"pivot": [0.01997, 27.175, 0.05221],
					"rotation": [0, 50, 0],
					"cubes": [
						{"origin": [-2.95503, 22.8, -2.99779], "size": [6, 2, 6], "pivot": [0.04497, 23.8, 0.00221], "rotation": [0, -47.5, 0], "uv": [43, 45]},
						{"origin": [0.54497, 23.8, -3.99779], "size": [0, 9, 8], "pivot": [0.54497, 23.8, 0.00221], "rotation": [7.5, -47.5, 0], "uv": [33, 34]},
						{"origin": [0.04497, 23.8, -3.99779], "size": [0, 9, 8], "pivot": [0.04497, 23.8, 0.00221], "rotation": [162.5, -87.5, -180], "uv": [40, 13]},
						{"origin": [0.04497, 23.8, -3.99779], "size": [0, 9, 8], "pivot": [0.04497, 23.8, 0.00221], "rotation": [-15, -22.5, 0], "uv": [40, 13]},
						{"origin": [-0.55503, 23.8, -3.79779], "size": [0, 9, 8], "pivot": [-0.55503, 23.8, 0.20221], "rotation": [17.5, 42.5, 0], "uv": [33, 34]},
						{"origin": [-2.36604, 23.7047, -5.07886], "size": [0, 9, 8], "pivot": [-0.55503, 23.8, 0.20221], "rotation": [178.00574, 22.46056, 177.54828], "uv": [33, 34]}
					]
				},
				{
					"name": "neck",
					"parent": "torso",
					"pivot": [0, 11.8, -6],
					"cubes": [
						{"origin": [-2, 10, -10], "size": [4, 4, 5], "uv": [56, 13]}
					]
				},
				{
					"name": "neck_2",
					"parent": "neck",
					"pivot": [0, 10, -10],
					"rotation": [-33, 0, 0],
					"cubes": [
						{"origin": [-2, 10, -14], "size": [4, 4, 4], "inflate": 0.01, "uv": [63, 49]}
					]
				},
				{
					"name": "neck_3",
					"parent": "neck_2",
					"pivot": [0, 10, -14],
					"rotation": [-57, 0, 0],
					"cubes": [
						{"origin": [-2, 10, -18], "size": [4, 4, 4], "inflate": 0.02, "uv": [32, 60]}
					]
				},
				{
					"name": "head",
					"parent": "neck_3",
					"pivot": [0, 12.08828, -17.93149],
					"cubes": [
						{"origin": [-3.5, 8.48828, -24.93149], "size": [7, 6, 7], "uv": [40, 0]},
						{"origin": [-4.32028, 10.10679, -22.03149], "size": [2, 4, 4], "pivot": [-3.7, 12.48828, -19.93149], "rotation": [0, 0, -17.5], "uv": [64, 22]},
						{"origin": [2.32028, 10.10679, -22.03149], "size": [2, 4, 4], "pivot": [3.7, 12.48828, -19.93149], "rotation": [0, 0, 17.5], "uv": [64, 22], "mirror": true}
					]
				},
				{
					"name": "high_jaw",
					"parent": "head",
					"pivot": [0, 8.48828, -24.93149],
					"rotation": [42.5, 0, 0],
					"cubes": [
						{"origin": [-3, 2.48828, -24.03149], "size": [6, 6, 4], "pivot": [0, 8.48828, -24.93149], "rotation": [-26.5, 0, 0], "uv": [44, 53]},
						{"origin": [-1, 5.29683, -25.01845], "size": [2, 2, 0], "inflate": 0.01, "pivot": [0, 6.29683, -25.01845], "rotation": [-26.5, 0, 0], "uv": [9, 23]},
						{"origin": [-2.5, 3.68595, -25.82161], "size": [1, 2, 0], "inflate": 0.01, "pivot": [-2, 4.68595, -25.82161], "rotation": [-26.15136, -4.44381, -8.96739], "uv": [0, 11]},
						{"origin": [1.5, 3.68595, -25.82161], "size": [1, 2, 0], "inflate": 0.01, "pivot": [2, 4.68595, -25.82161], "rotation": [-26.15136, 4.44381, 8.96739], "uv": [0, 3]},
						{"origin": [-3, 2.48828, -20.03149], "size": [6, 0, 2], "pivot": [0, 8.48828, -24.93149], "rotation": [-26.5, 0, 0], "uv": [0, 3]},
						{"origin": [-3, 2.48828, -20.03149], "size": [0, 4, 2], "pivot": [0, 8.48828, -24.93149], "rotation": [-26.5, 0, 0], "uv": [0, 19]},
						{"origin": [3, 2.48828, -20.03149], "size": [0, 4, 2], "pivot": [1, 8.48828, -24.93149], "rotation": [-26.5, 0, 0], "uv": [10, 3]}
					]
				},
				{
					"name": "lower_jaw",
					"parent": "high_jaw",
					"pivot": [0, 5.31837, -20.06688],
					"cubes": [
						{"origin": [-2.5, 0.68465, -20.73479], "size": [5, 5, 3], "pivot": [0, 5.31837, -20.06688], "rotation": [-49, 0, 0], "uv": [61, 60]}
					]
				},
				{
					"name": "eye_right",
					"parent": "head",
					"pivot": [-4, 9.78828, -22.23149],
					"rotation": [0, 0, 4]
				},
				{
					"name": "eyelid_right",
					"parent": "eye_right",
					"pivot": [-4, 9.78828, -22.23149],
					"cubes": [
						{"origin": [-4.4, 5.58828, -25.33149], "size": [0, 6, 5], "inflate": 0.015, "pivot": [-4, 9.78828, -22.23149], "rotation": [25.94102, 8.42106, -20.94102], "uv": [0, 0]}
					]
				},
				{
					"name": "eye_right2",
					"parent": "eye_right",
					"pivot": [-4, 9.78828, -22.23149],
					"cubes": [
						{"origin": [-4.4, 5.78828, -23.73149], "size": [0, 5, 4], "inflate": 0.01, "pivot": [-4, 9.78828, -22.23149], "rotation": [20.94102, 8.42106, -20.94102], "uv": [0, 38]}
					]
				},
				{
					"name": "eyeglobe",
					"parent": "eye_right",
					"pivot": [-4, 9.78828, -22.23149],
					"cubes": [
						{"origin": [-4.4, 5.78828, -23.73149], "size": [2, 4, 4], "pivot": [-4, 9.78828, -22.23149], "rotation": [20.94102, 8.42106, -20.94102], "uv": [48, 63]}
					]
				},
				{
					"name": "eye_left",
					"parent": "head",
					"pivot": [4, 9.78828, -22.23149],
					"rotation": [0, 0, -4]
				},
				{
					"name": "eyelid_left",
					"parent": "eye_left",
					"pivot": [4, 9.78828, -22.23149],
					"cubes": [
						{"origin": [4.4, 5.58828, -25.33149], "size": [0, 6, 5], "inflate": 0.015, "pivot": [4, 9.78828, -22.23149], "rotation": [25.94102, -8.42106, 20.94102], "uv": [0, 0], "mirror": true}
					]
				},
				{
					"name": "eye_left2",
					"parent": "eye_left",
					"pivot": [4, 9.78828, -22.23149],
					"cubes": [
						{"origin": [4.4, 5.78828, -23.73149], "size": [0, 5, 4], "inflate": 0.01, "pivot": [4, 9.78828, -22.23149], "rotation": [20.94102, -8.42106, 20.94102], "uv": [0, 38], "mirror": true}
					]
				},
				{
					"name": "eyeglobe2",
					"parent": "eye_left",
					"pivot": [4, 9.78828, -22.23149],
					"cubes": [
						{"origin": [2.4, 5.78828, -23.73149], "size": [2, 4, 4], "pivot": [4, 9.78828, -22.23149], "rotation": [20.94102, -8.42106, 20.94102], "uv": [48, 63], "mirror": true}
					]
				},
				{
					"name": "tail_1",
					"parent": "torso",
					"pivot": [0, 11.3, 4.8],
					"rotation": [20, 0, 0],
					"cubes": [
						{"origin": [-2, 9.8, 3.5], "size": [4, 3, 7], "uv": [49, 23]}
					]
				},
				{
					"name": "tail_2",
					"parent": "tail_1",
					"pivot": [0, 11.3, 9.8],
					"rotation": [12.5, 0, 0],
					"cubes": [
						{"origin": [-1, 10.3, 9.5], "size": [2, 2, 5], "uv": [0, 21]}
					]
				},
				{
					"name": "arms",
					"parent": "body",
					"pivot": [0, 4, 0]
				},
				{
					"name": "arm_right",
					"parent": "arms",
					"pivot": [-5.3, 9.6, -4],
					"rotation": [17, -5.188, 16.73634],
					"cubes": [
						{"origin": [-8, 4.6, -6], "size": [4, 6, 4], "uv": [16, 60]},
						{"origin": [-8, 7, -4.7], "size": [0, 2, 2], "inflate": 0.01, "pivot": [-8, 8.7, -4], "rotation": [7.5, 0, 0], "uv": [9, 19]}
					]
				},
				{
					"name": "arm_right_2",
					"parent": "arm_right",
					"pivot": [-6, 4.6, -2],
					"rotation": [-30, 0, 0],
					"cubes": [
						{"origin": [-8, -1.4, -6], "size": [4, 6, 4], "inflate": 0.01, "pivot": [-6.5, 4.6, -2], "rotation": [-12.5, 0, 0], "uv": [0, 60]},
						{"origin": [-8, 3.01824, -5.44745], "size": [0, 1, 1], "inflate": 0.012, "pivot": [-8, 2.91824, -4.24745], "rotation": [-15.5, 0, 0], "uv": [0, 1]}
					]
				},
				{
					"name": "arm_right_3",
					"parent": "arm_right_2",
					"pivot": [-5.639, -0.94597, -4.95814],
					"rotation": [12, 8.68205, -14.96369],
					"cubes": [
						{"origin": [-8.20792, -1.90788, -7.5248], "size": [5, 3, 5], "uv": [49, 37]},
						{"origin": [-8.20792, -1.90788, -10.2248], "size": [5, 0, 3], "inflate": 0.01, "uv": [0, 28]},
						{"origin": [-8.10792, -1.90788, -8.3248], "size": [5, 0, 3], "pivot": [-7.20792, -2.90788, -4.7248], "rotation": [0, 90, 0], "uv": [0, 11]},
						{"origin": [-11.20792, -1.90788, -11.4248], "size": [5, 0, 3], "pivot": [-7.20792, -2.90788, -4.7248], "rotation": [0, -90, 0], "uv": [0, 0]}
					]
				},
				{
					"name": "arm_left",
					"parent": "arms",
					"pivot": [5.3, 9.6, -4],
					"rotation": [17, 5.188, -16.73634],
					"cubes": [
						{"origin": [4, 4.6, -6], "size": [4, 6, 4], "uv": [16, 60], "mirror": true},
						{"origin": [8, 7, -4.7], "size": [0, 2, 2], "inflate": 0.01, "pivot": [8, 8.7, -4], "rotation": [7.5, 0, 0], "uv": [9, 19], "mirror": true}
					]
				},
				{
					"name": "arm_left_2",
					"parent": "arm_left",
					"pivot": [6, 4.6, -2],
					"rotation": [-30, 0, 0],
					"cubes": [
						{"origin": [4, -1.4, -6], "size": [4, 6, 4], "inflate": 0.01, "pivot": [6.5, 4.6, -2], "rotation": [-12.5, 0, 0], "uv": [0, 60], "mirror": true},
						{"origin": [8, 3.01824, -5.44745], "size": [0, 1, 1], "inflate": 0.012, "pivot": [8, 2.91824, -4.24745], "rotation": [-15.5, 0, 0], "uv": [0, 1], "mirror": true}
					]
				},
				{
					"name": "arm_left_3",
					"parent": "arm_left_2",
					"pivot": [5.639, -0.94597, -4.95814],
					"rotation": [12, -8.68205, 14.96369],
					"cubes": [
						{"origin": [3.20792, -1.90788, -7.5248], "size": [5, 3, 5], "uv": [49, 37], "mirror": true},
						{"origin": [3.20792, -1.90788, -10.2248], "size": [5, 0, 3], "inflate": 0.01, "uv": [0, 28], "mirror": true},
						{"origin": [3.10792, -1.90788, -8.3248], "size": [5, 0, 3], "pivot": [7.20792, -2.90788, -4.7248], "rotation": [0, -90, 0], "uv": [0, 11], "mirror": true},
						{"origin": [6.20792, -1.90788, -11.4248], "size": [5, 0, 3], "pivot": [7.20792, -2.90788, -4.7248], "rotation": [0, 90, 0], "uv": [0, 0], "mirror": true}
					]
				},
				{
					"name": "arm_right2",
					"parent": "arms",
					"pivot": [-5.3, 9.6, 5],
					"rotation": [44.5, -5.188, 16.73634],
					"cubes": [
						{"origin": [-8, 4.6, 3], "size": [4, 6, 4], "uv": [16, 60]},
						{"origin": [-8, 6.64952, 3.9701], "size": [0, 1, 1], "uv": [0, 0], "mirror": true}
					]
				},
				{
					"name": "arm_right_4",
					"parent": "arm_right2",
					"pivot": [-6, 4.6, 7],
					"rotation": [-32.5, 0, 0],
					"cubes": [
						{"origin": [-8, -1.4, 3], "size": [4, 6, 4], "inflate": 0.01, "pivot": [-6.5, 4.6, 7], "rotation": [-7.60452, -0.81757, -0.64134], "uv": [0, 60]},
						{"origin": [-8, 0.9, 3.6], "size": [0, 2, 2], "inflate": 0.01, "pivot": [-8, 2, 4.6], "rotation": [-7.5, 0, 0], "uv": [10, 7], "mirror": true}
					]
				},
				{
					"name": "arm_right_5",
					"parent": "arm_right_4",
					"pivot": [-5.40957, -1.69101, 3.8622],
					"rotation": [-13.69323, 7.52713, -19.87767],
					"cubes": [
						{"origin": [-7.97849, -2.65292, 1.29554], "size": [5, 3, 5], "uv": [49, 37]},
						{"origin": [-7.97849, -2.65292, -1.40446], "size": [5, 0, 3], "inflate": 0.01, "uv": [0, 28]},
						{"origin": [-7.87849, -2.65292, 0.49554], "size": [5, 0, 3], "pivot": [-6.97849, -3.65292, 4.09554], "rotation": [0, 90, 0], "uv": [0, 11]},
						{"origin": [-10.97849, -2.65292, -2.60446], "size": [5, 0, 3], "pivot": [-6.97849, -3.65292, 4.09554], "rotation": [0, -90, 0], "uv": [0, 0]}
					]
				},
				{
					"name": "arm_left2",
					"parent": "arms",
					"pivot": [5.3, 9.6, 5],
					"rotation": [44.5, 5.188, -16.73634],
					"cubes": [
						{"origin": [4, 4.6, 3], "size": [4, 6, 4], "uv": [16, 60], "mirror": true},
						{"origin": [8, 6.64952, 3.9701], "size": [0, 1, 1], "inflate": 0.01, "uv": [0, 0]}
					]
				},
				{
					"name": "arm_left_4",
					"parent": "arm_left2",
					"pivot": [6, 4.6, 7],
					"rotation": [-32.5, 0, 0],
					"cubes": [
						{"origin": [4, -1.4, 3], "size": [4, 6, 4], "inflate": 0.01, "pivot": [6.5, 4.6, 7], "rotation": [-7.60452, 0.81757, 0.64134], "uv": [0, 60], "mirror": true},
						{"origin": [8, 0.9, 3.6], "size": [0, 2, 2], "inflate": 0.01, "pivot": [8, 2, 4.6], "rotation": [-7.5, 0, 0], "uv": [10, 7]}
					]
				},
				{
					"name": "arm_left_5",
					"parent": "arm_left_4",
					"pivot": [5.40957, -1.69101, 3.8622],
					"rotation": [-13.69323, -7.52713, 19.87767],
					"cubes": [
						{"origin": [2.97849, -2.65292, 1.29554], "size": [5, 3, 5], "uv": [49, 37], "mirror": true},
						{"origin": [2.97849, -2.65292, -1.40446], "size": [5, 0, 3], "inflate": 0.01, "uv": [0, 28], "mirror": true},
						{"origin": [2.87849, -2.65292, 0.49554], "size": [5, 0, 3], "pivot": [6.97849, -3.65292, 4.09554], "rotation": [0, -90, 0], "uv": [0, 11], "mirror": true},
						{"origin": [5.97849, -2.65292, -2.60446], "size": [5, 0, 3], "pivot": [6.97849, -3.65292, 4.09554], "rotation": [0, 90, 0], "uv": [0, 0], "mirror": true}
					]
				}
			]
		}
	]
}